LICENSE
MANIFEST.in
README.md
setup.py
fatkun/__init__.py
fatkun/converter.py
fatkun/downloader.py
fatkun/example.py
fatkun/fatkun.py
fatkun/url_lib.pyd
fatkun.egg-info/PKG-INFO
fatkun.egg-info/SOURCES.txt
fatkun.egg-info/dependency_links.txt
fatkun.egg-info/requires.txt
fatkun.egg-info/top_level.txt