Metadata-Version: 2.1
Name: fatkun
Version: 0.1.4
Summary: target resourse file downloader and converter
Home-page: https://github.com/
Author: yan wang
Author-email: 1449349985@qq.com
License: MIT
Classifier: License :: OSI Approved :: MIT License
Classifier: Programming Language :: Python
Classifier: Programming Language :: Python :: 3
Classifier: Programming Language :: Python :: 3.9
Classifier: Programming Language :: Python :: Implementation :: CPython
Classifier: Programming Language :: Python :: Implementation :: PyPy
Requires-Python: >=3.9.0
License-File: LICENSE
Requires-Dist: requests==2.31.0
